<?xml version="1.0" encoding="UTF-8"?>
<repomd xmlns="http://linux.duke.edu/metadata/repo" xmlns:rpm="http://linux.duke.edu/metadata/rpm">
  <revision>1776641568</revision>
  <data type="primary">
    <checksum type="sha256">6739532ece97ddf441d6ad776461ddadf50a589a778e12dac08b2b8d5c27a33b</checksum>
    <open-checksum type="sha256">9ac71e0f4e138a3c6c2e181a694bc11b7489dbcfef7fd66c69752e096b3fbef2</open-checksum>
    <location href="repodata/primary.xml.gz"/>
    <timestamp>1776641568</timestamp>
    <size>808</size>
    <open-size>1566</open-size>
  </data>
  <data type="filelists">
    <checksum type="sha256">e0b8b64e46c8ec66c4d5fc75b57bdd467c3db9c5b24d5a1db6f1491e10e15bd4</checksum>
    <open-checksum type="sha256">cf74991cf00b7f97f47595039e17182bcb03b9a229ae33d0fd115da4de1ef47e</open-checksum>
    <location href="repodata/filelists.xml.gz"/>
    <timestamp>1776641568</timestamp>
    <size>30621</size>
    <open-size>410399</open-size>
  </data>
  <data type="other">
    <checksum type="sha256">82c24f489663e8a32a13e7328b14017bcdd41a6c52b34cce980d65cf01d9934c</checksum>
    <open-checksum type="sha256">7eeaa549facab2d106828bcbe625f1a62c8ca4c8723ea75d7143442891584153</open-checksum>
    <location href="repodata/other.xml.gz"/>
    <timestamp>1776641568</timestamp>
    <size>233</size>
    <open-size>291</open-size>
  </data>
  <data type="primary_db">
    <checksum type="sha256">6565283186b434f0db65c51745378831ac00769a88a1ba6a5dbc5604bafe181f</checksum>
    <open-checksum type="sha256">7a7e0f533ffcecf6a187ab67fc14008aca6a84d7ad906e29787f81c88971b7c3</open-checksum>
    <location href="repodata/primary.sqlite.bz2"/>
    <timestamp>1776641568</timestamp>
    <size>2019</size>
    <open-size>106496</open-size>
    <database_version>10</database_version>
  </data>
  <data type="filelists_db">
    <checksum type="sha256">a2b50561052e24cb2089f704f37811163b205efbe4e27d65f43974665596a641</checksum>
    <open-checksum type="sha256">558da88089a14202527b1cb97a66835f382c1d648b593e959ebe51867971402c</open-checksum>
    <location href="repodata/filelists.sqlite.bz2"/>
    <timestamp>1776641568</timestamp>
    <size>38415</size>
    <open-size>249856</open-size>
    <database_version>10</database_version>
  </data>
  <data type="other_db">
    <checksum type="sha256">311799637ab5d57d13f864e39f1114daefcb7e8ed81adf173f298a9dd7a7fa0b</checksum>
    <open-checksum type="sha256">ec97b6ef906930b53a5f77ca5599ec01d69c06404db9efcc23d0b0a53b4f0c83</open-checksum>
    <location href="repodata/other.sqlite.bz2"/>
    <timestamp>1776641568</timestamp>
    <size>663</size>
    <open-size>24576</open-size>
    <database_version>10</database_version>
  </data>
</repomd>
